smart_prompt_mcp/__init__.py
smart_prompt_mcp/__main__.py
smart_prompt_mcp-0.1.5.dist-info/METADATA
smart_prompt_mcp-0.1.5.dist-info/WHEEL
smart_prompt_mcp-0.1.5.dist-info/entry_points.txt
smart_prompt_mcp-0.1.5.dist-info/top_level.txt
smart_prompt_mcp-0.1.5.dist-info/RECORD
