Metadata-Version: 2.4
Name: smart_prompt_mcp
Version: 0.1.5
Summary: 一个智能提示词MCP服务器
Author: MuJiayi
Keywords: mcp,prompt,template
Requires-Python: >=3.10
Requires-Dist: fastmcp
Dynamic: author
Dynamic: description
Dynamic: description-content-type
Dynamic: keywords
Dynamic: requires-dist
Dynamic: requires-python
Dynamic: summary
